win_nic/__init__.py
win_nic/_network_adapters.py
win_nic/_nic.py
win_nic/_utils.py
win_nic/enums/__init__.py
win_nic/enums/nic_adapter_type.py
win_nic/enums/nic_availability.py
win_nic/enums/nic_config_manager_error_code.py
win_nic/enums/nic_net_connection_status.py
win_nic/tests/__init__.py
win_nic/tests/test_network_adapters.py
win_nic/tests/test_nic.py
win_nic-2.0.1.dist-info/LICENSE
win_nic-2.0.1.dist-info/METADATA
win_nic-2.0.1.dist-info/WHEEL
win_nic-2.0.1.dist-info/top_level.txt
win_nic-2.0.1.dist-info/RECORD
