Metadata-Version: 2.1
Name: win-nic
Version: 2.0.1
Summary: Python package to interface with network intetrface cards (NICs) on Windows-based computers.
Home-page: https://github.com/TNThieding/win-nic
Author: Tyler N. Thieding
Author-email: python@thieding.com
Maintainer: Tyler N. Thieding
Maintainer-email: python@thieding.com
License: MIT License
Download-URL: https://github.com/TNThieding/win-nic
Platform: UNKNOWN
Classifier: Development Status :: 5 - Production/Stable
Classifier: Intended Audience :: Developers
Classifier: Intended Audience :: System Administrators
Classifier: License :: OSI Approved :: MIT License
Classifier: Natural Language :: English
Classifier: Operating System :: Microsoft :: Windows
Classifier: Programming Language :: Python
Classifier: Topic :: System :: Networking
Requires-Dist: enum34
Requires-Dist: texttable
